rest_framework_latex/__init__.py
rest_framework_latex/markdown.py
rest_framework_latex/renderers.py
rest_framework_latex/utils.py
rest_framework_latex/templatetags/__init__.py
rest_framework_latex/templatetags/rest_framework_latex.py
rest_framework_latex-0.1.0.dist-info/DESCRIPTION.rst
rest_framework_latex-0.1.0.dist-info/METADATA
rest_framework_latex-0.1.0.dist-info/RECORD
rest_framework_latex-0.1.0.dist-info/WHEEL
rest_framework_latex-0.1.0.dist-info/metadata.json
rest_framework_latex-0.1.0.dist-info/top_level.txt
