Metadata-Version: 2.0
Name: rest-framework-latex
Version: 0.1.0
Summary: A LaTeX renderer for Django REST Framework
Home-page: https://github.com/mypebble/rest-framework-latex
Author: Pebble
Author-email: sysadmin@mypebble.co.uk
License: UNKNOWN
Platform: UNKNOWN
Requires-Dist: django
Requires-Dist: djangorestframework
Requires-Dist: six
